obs_ws_rc-2.3.0.dist-info/DESCRIPTION.rst
obs_ws_rc-2.3.0.dist-info/METADATA
obs_ws_rc-2.3.0.dist-info/RECORD
obs_ws_rc-2.3.0.dist-info/WHEEL
obs_ws_rc-2.3.0.dist-info/metadata.json
obs_ws_rc-2.3.0.dist-info/top_level.txt
obswsrc/__init__.py
obswsrc/client.py
obswsrc/events.py
obswsrc/logs.py
obswsrc/protocol.json
obswsrc/protocol.py
obswsrc/requests.py
obswsrc/struct.py
obswsrc/types.py
