Metadata-Version: 2.0
Name: obs-ws-rc
Version: 2.3.0
Summary: asyncio-based Python 3.5+ client to obs-websocket plugin for OBS Studio
Home-page: https://github.com/KirillMysnik/obs-ws-rc
Author: Kirill Mysnik
Author-email: kirill@mysnik.com
License: MIT
Keywords: obs obs-websocket
Platform: UNKNOWN
Classifier: Development Status :: 5 - Production/Stable
Classifier: Intended Audience :: Developers
Classifier: Topic :: Software Development :: Libraries :: Python Modules
Classifier: Topic :: Multimedia :: Video
Classifier: License :: OSI Approved :: MIT License
Classifier: Operating System :: OS Independent
Classifier: Programming Language :: Python :: 3 :: Only
Classifier: Programming Language :: Python :: 3.5
Classifier: Programming Language :: Python :: 3.6
Requires-Python: >=3.5
Requires-Dist: websockets
